Metadata-Version: 1.0
Name: cgtools
Version: 0.4.6
Summary: A simple tools for CG software applications
Home-page: http://www.tdace.com
Author: ZhangLiGang
Author-email: 394452216@qq.com
License: GPL Licence
Keywords: autodesk,3dsmax,vray,corona
Platform: UNKNOWN
